gfile/__init__.py
gfile/__main__.py
gfile/cmd.py
gfile/gfile.py
gigafile-3.2.5.dist-info/licenses/LICENSE
gigafile-3.2.5.dist-info/METADATA
gigafile-3.2.5.dist-info/WHEEL
gigafile-3.2.5.dist-info/entry_points.txt
gigafile-3.2.5.dist-info/top_level.txt
gigafile-3.2.5.dist-info/RECORD
