Metadata-Version: 2.4
Name: gigafile
Version: 3.2.5
Summary: A python module to download and upload from gigafile.nu
Home-page: https://github.com/fireattack/gfile
Author: Sraqzit, fireattack
License: GNU 3.0
Project-URL: Source, https://github.com/fireattack/gfile
Project-URL: Tracker, https://github.com/fireattack/gfile/issues
Platform: Linux
Platform: Mac OS-X
Platform: Windows
Platform: Unix
License-File: LICENSE
Requires-Dist: requests>=2.25.1
Requires-Dist: requests_toolbelt>=0.9.1
Requires-Dist: tqdm>=4.61.2
Requires-Dist: beautifulsoup4>=4
Dynamic: author
Dynamic: license-file
Dynamic: platform
Dynamic: requires-dist
Dynamic: summary
